ipython_polypheny-0.1.3.dist-info/licenses/LICENSE
poly/__init__.py
poly/http_interface.py
poly/poly_magic.py
poly/poly_result.py
ipython_polypheny-0.1.3.dist-info/METADATA
ipython_polypheny-0.1.3.dist-info/WHEEL
ipython_polypheny-0.1.3.dist-info/top_level.txt
ipython_polypheny-0.1.3.dist-info/RECORD
