Metadata-Version: 2.4
Name: ipython-polypheny
Version: 0.1.3
Summary: Access Polypheny via IPython magics
Home-page: https://polypheny.org/
Author: The Polypheny Project
Author-email: mail@polypheny.org
License: Apache License, Version 2.0
Keywords: polypheny,ipython
Classifier: License :: OSI Approved :: Apache Software License
Classifier: Programming Language :: Python :: 3
License-File: LICENSE
Requires-Dist: ipython>=8.0.0
Requires-Dist: requests>=2.25.0
Requires-Dist: prettytable>=3.8.0
Dynamic: license-file
